rich_rst/__init__.py
rich_rst/__main__.py
rich_rst-1.3.0.dist-info/LICENSE
rich_rst-1.3.0.dist-info/METADATA
rich_rst-1.3.0.dist-info/WHEEL
rich_rst-1.3.0.dist-info/top_level.txt
rich_rst-1.3.0.dist-info/RECORD
