Metadata-Version: 2.1
Name: rich-rst
Version: 1.3.0
Summary: A beautiful reStructuredText renderer for rich
Home-page: https://wasi-master.github.io/rich-rst
Author: Wasi Master
Author-email: arianmollik323@gmail.com
License: MIT
Project-URL: Bug Tracker, https://github.com/wasi-master/rich-rst/issues
Project-URL: Source, https://github.com/wasi-master/rich-rst
Project-URL: Documentation, https://rich-rst.readthedocs.io/en/latest/
Project-URL: Say Thanks, https://saythanks.io/to/wasi-master
Keywords: richrst,restructuredtextrich restructuredtextrich-restructuredtextrich rstrich-rst
Classifier: Programming Language :: Python
Classifier: Programming Language :: Python :: 3
Classifier: Programming Language :: Python :: 3.6
Classifier: Programming Language :: Python :: 3.7
Classifier: Programming Language :: Python :: 3.8
Classifier: Programming Language :: Python :: 3.9
Classifier: Programming Language :: Python :: 3.10
Classifier: Programming Language :: Python :: 3.11
Classifier: Programming Language :: Python :: 3.12
Classifier: License :: OSI Approved :: MIT License
Classifier: Operating System :: OS Independent
Classifier: Development Status :: 5 - Production/Stable
Classifier: Intended Audience :: Developers
Classifier: Natural Language :: English
Requires-Python: >=3.6
License-File: LICENSE
Requires-Dist: docutils
Requires-Dist: rich >=12.0.0
